wave_monitor/__init__.py
wave_monitor/assets/icon.svg
wave_monitor/assets/style.qss
wave_monitor/client.py
wave_monitor/constants.py
wave_monitor/proto.py
wave_monitor/window.py
wavemonitor-0.4.2.dist-info/WHEEL
wavemonitor-0.4.2.dist-info/entry_points.txt
wavemonitor-0.4.2.dist-info/METADATA
wavemonitor-0.4.2.dist-info/RECORD
