Metadata-Version: 2.3
Name: wavemonitor
Version: 0.4.2
Summary: A simple GUI for monitoring waveforms.
Author: Qiujv
Author-email: Qiujv <qiujv@outlook.com>
Classifier: Programming Language :: Python :: 3
Classifier: License :: OSI Approved :: MIT License
Requires-Dist: msgpack>=0.4.0
Requires-Dist: msgpack-numpy
Requires-Dist: numpy
Requires-Dist: pyqtgraph
Requires-Dist: pyside6>=6.7.0,!=6.9.1
Requires-Dist: typing-extensions
Requires-Python: >=3.9
Project-URL: Homepage, https://github.com/Qiujv/WaveMonitor
